fwie/__init__.py
fwie/_nbdev.py
fwie/core.py
fwie/fwie.py
fwie-0.0.2.dist-info/LICENSE
fwie-0.0.2.dist-info/METADATA
fwie-0.0.2.dist-info/WHEEL
fwie-0.0.2.dist-info/entry_points.txt
fwie-0.0.2.dist-info/top_level.txt
fwie-0.0.2.dist-info/RECORD
