Metadata-Version: 2.1
Name: fwie
Version: 0.0.2
Summary: An enhanced Fire Weather Index with atmospheric instability information
Home-page: https://github.com/mnpinto/fwie/tree/master/
Author: Miguel Pinto
Author-email: mnpinto@fc.ul.pt
License: Apache Software License 2.0
Keywords: Fire Weather Index,wildfires
Platform: UNKNOWN
Classifier: Development Status :: 4 - Beta
Classifier: Intended Audience :: Developers
Classifier: License :: OSI Approved :: Apache Software License
Classifier: Natural Language :: English
Classifier: Programming Language :: Python :: 3.6
Classifier: Programming Language :: Python :: 3.7
Classifier: Programming Language :: Python :: 3.8
Requires-Python: >=3.6
